[
  {
    "id": "andrew-magiril",
    "teamName": "Brent's Daddy",
    "owners": ["Andrew Magirl"],
    "previousRank": 1,
    "picks": ["POR", "USA", "GER", "NED", "EGY"]
  },
  {
    "id": "allen-fredrick",
    "teamName": "Metcalf Hurts",
    "owners": ["Allen Fredrick"],
    "previousRank": 2,
    "picks": ["ESP", "NED", "JPN", "URU", "KOR"]
  },
  {
    "id": "robby-copeland",
    "teamName": "Team Camouflage Cndm",
    "owners": ["Robby Copeland"],
    "previousRank": 3,
    "picks": ["ESP", "ARG", "AUS", "QAT", "KSA"]
  },
  {
    "id": "michael-hebert",
    "teamName": "Team Megatronless",
    "owners": ["Michael Hebert"],
    "previousRank": 4,
    "picks": []
  },
  {
    "id": "brent-hull-allie-hull",
    "teamName": "Bijan Mustard",
    "owners": ["Brent Hull", "Allie Hull"],
    "previousRank": 5,
    "picks": ["FRA", "NED", "COL", "PAR", "AUS"]
  },
  {
    "id": "jon-koyn",
    "teamName": "Team koyn",
    "owners": ["Jon Koyn"],
    "previousRank": 6,
    "picks": []
  },
  {
    "id": "eric-broadworth",
    "teamName": "Team Godfather",
    "owners": ["Eric Broadworth"],
    "previousRank": 7,
    "picks": ["FRA", "NED", "USA", "CAN", "EGY"]
  },
  {
    "id": "jordan-koyn",
    "teamName": "Team Jordan",
    "owners": ["Jordan Koyn"],
    "previousRank": 8,
    "picks": []
  },
  {
    "id": "cory-pahl",
    "teamName": "Team Pahl",
    "owners": ["Cory Pahl"],
    "previousRank": 9,
    "picks": ["BRA", "NED", "MAR", "JPN", "SUI"]
  },
  {
    "id": "randy-hebert",
    "teamName": "Team Choo Choo",
    "owners": ["Randy Hebert"],
    "previousRank": 10,
    "picks": ["ENG", "NED", "USA", "JPN", "MEX"]
  },
  {
    "id": "nick-mcbride",
    "teamName": "Hubba Hubba CD's Nutz",
    "owners": ["Nick McBride"],
    "previousRank": 11,
    "picks": ["ARG", "USA", "AUT", "MEX", "POR"]
  },
  {
    "id": "daniel-mack",
    "teamName": "Team Mack",
    "owners": ["Daniel Mack"],
    "previousRank": 12,
    "picks": ["ESP", "COL", "MAR", "ECU", "USA"]
  }
]
